{
  "iteration": 7,
  "history": [
    {
      "iter": 1,
      "timestamp": "2026-03-12T00:34:22.857930",
      "target_section": "sec25_c_電話の流れと時間間隔.md",
      "feedback_snippet": "電話の流れと時間感覚のところについてなんだけど、これアイスブレイクのところは一旦良くて、この教官トーク、格上トークっていうところをもうちょっと充実させていきたく",
      "critique_summary": "電話での「共感トーク」と「格上トーク」のセクションについて、役割と解説の構造は維持しつつ、女の子に心を開かせ、かつ間接的に格上感をアピールするための具体的な実践テクニックを充実させたい。",
      "validation_score": 95,
      "verdict": "pass",
      "coherence_applied": true
    },
    {
      "iter": 2,
      "timestamp": "2026-03-12T12:52:15.414076",
      "target_section": "sec25_c_電話の流れと時間間隔.md",
      "feedback_snippet": "えっとそもそも構造化が間違っていてえっとまあ大きく二つに分かれるこの共感トーク角栄トークっていうところについては教官と角栄大きく二つに分かれるんだけれどもえ共感",
      "critique_summary": "「共感トーク・格上トーク」のセクション構成がユーザーの意図と異なっており、各トークの構造と具体例の修正、および抽象概念の説明の強化が求められています。",
      "validation_score": 95,
      "verdict": "pass",
      "coherence_applied": false
    },
    {
      "iter": 3,
      "timestamp": "2026-03-12T13:05:42.547114",
      "target_section": "sec25_c_電話の流れと時間間隔.md",
      "feedback_snippet": "基本的にはかなり良い形で構造ができているので全体の論理とか構成というのはこれでよくって、えっと加えて一部一部というか一行一行一段落一段落がちょっと長い気がしてい",
      "critique_summary": "一部の段落が長く、読みづらさを感じるため、空白行を活用し、1段落2文程度にすることで可読性を上げたい。",
      "validation_score": 95,
      "verdict": "pass",
      "coherence_applied": true
    },
    {
      "iter": 4,
      "timestamp": "2026-03-12T13:12:58.687068",
      "target_section": "sec26_iii_恋愛トーク（10〜15分）.md",
      "feedback_snippet": "恋愛トークの部分についてなんだけどうんそうだなえっとまず絶対的に会えないのはこの人はモテるでも政治思想という印象を植えつけるっていうのは絶対間違えてこんなわけわ",
      "critique_summary": "恋愛トークの目的と、「誠実さ」に関する表現が記事の戦略とずれているため、修正が必要。",
      "validation_score": 95,
      "verdict": "pass",
      "coherence_applied": false
    },
    {
      "iter": 5,
      "timestamp": "2026-03-12T13:18:44.105116",
      "target_section": "sec01_はじめに.md",
      "feedback_snippet": "あまずですます調で整えて欲しいって言うのが一転と女の子は気持ちよく話せる鉄板テーマになってるのはもうあとそうそうそうそうなんだけどそうだあとまあ結局恋愛とかそれ",
      "critique_summary": "記事全体の文体を「ですます調」に統一し、電話における「恋愛トーク」と「エロトーク」の重要性を強調し、その導入タイミングを早め、セクションの構成を改善する要望。",
      "validation_score": 95,
      "verdict": "pass",
      "coherence_applied": false
    },
    {
      "iter": 6,
      "timestamp": "2026-03-12T13:28:54.547998",
      "target_section": "sec26_iii_恋愛トーク（10〜15分）.md",
      "feedback_snippet": "あまずですます調で整えて欲しいって言うのが一転と女の子は気持ちよく話せる鉄板テーマになってるのはもうあとそうそうそうそうなんだけどそうだあとまあ結局恋愛とかそれ",
      "critique_summary": "恋愛トークの役割を明確化し、早い段階での恋愛対象としての認識づけを強化。全体的にですます調に統一し、構成を改善。",
      "validation_score": 95,
      "verdict": "pass",
      "coherence_applied": false
    },
    {
      "iter": 7,
      "timestamp": "2026-03-12T13:58:22.018633",
      "target_section": "sec27_iv_（必要あれば）エロトーク（10〜15分）.md",
      "feedback_snippet": "えっとまあ大まかな構造化として佳正ですでその上でええとまあまた同じように一部一部一行一行いじゃなく一段落がちょっと長すぎるのでまあ一応中当たり2分程度で押さえる",
      "critique_summary": "「エロトーク」セクションは、段落が長く読みにくく、文体が統一されていません。また、具体的な会話例の前に抽象的な概念説明が不足しており、内容の構造化も必要です。タイトルも内容に合わせたものに見直すことを検討してください。",
      "validation_score": 95,
      "verdict": "pass",
      "coherence_applied": false
    }
  ]
}